mazesolverhk/__init__.py
mazesolverhk-0.1.dist-info/License.txt
mazesolverhk-0.1.dist-info/METADATA
mazesolverhk-0.1.dist-info/WHEEL
mazesolverhk-0.1.dist-info/top_level.txt
mazesolverhk-0.1.dist-info/RECORD
